{
	"slidepics": {
		"value": [{
			"title": "Gooseberry and Elderflower Tower Cakes",
			"image": "images/baner.jpg",
			"link": "article/1.html",
			"description": "Although it isn't gooseberry season anymore, I thought I would publish this recipe now because it wo..."
		},{
			"title": "Gooseberry and Elderflower Tower Cakes",
			"image": "images/baner.jpg",
			"link": "article/1.html",
			"description": "Although it isn't gooseberry season anymore, I thought I would publish this recipe now because it wo..."
		}],
		"config" : {
			"width":900,
			"height":540,
			"limit":5	
		},
		"description": "大轮滚图",
		"type": "images"
	}, 
        "about_title": {
		"value": "关于我们",
		"description": "自定义“关于我们”",
		"type": "text"
	},
        "about_image": {
		"value": {
			"title": "关于我们",
			"image": "images/img.jpg",
			"link": "http://www.baidu.com/"
		},
		"config" : {
			"width":900,
			"height":540,
			"limit":5		
		},
		"description": "关于我们图片",
		"type": "image"
	},
        "about_description": {
		"value": "2005年，易尔通被百度授权建立了厦门地区\"百度客户销售服务中心\"，该服务中心为厦门地区的百度客户提供专业的服务。2007年11月，厦 并定做异形柜上百种规格... 2007年11月，厦 并定做异形柜上百种规格2007年11月，厦 并定做异形柜上百种规格2007上百种规格...",
		"description": "“关于我们”简介",
		"type": "textarea"
	}, 
         "contact_image": {
		"value": {
			"title": "联系我们",
			"image": "images/rimg_03.jpg",
			"link": "http://www.baidu.com/"
		},
		"config" : {
			"width":900,
			"height":540,
			"limit":5		
		},
		"description": "联系我们图片",
		"type": "image"
	},
        "serv_image": {
		"value": {
			"title": "服务项目",
			"image": "images/rimg_06.jpg",
			"link": "http://www.baidu.com/"
		},
		"config" : {
			"width":900,
			"height":540,
			"limit":5		
		},
		"description": "服务项目图片",
		"type": "image"
	},
         "pro_image": {
		"value": {
			"title": "产品中心",
			"image": "images/rimg_09.jpg",
			"link": "http://www.baidu.com/"
		},
		"config" : {
			"width":900,
			"height":540,
			"limit":5		
		},
		"description": "案例展示图片",
		"type": "image"
	},
	"list1": {
		"value": {
		},
		"config": {
			"limit": 4,
			"star_only": 0
		},
		"description": "第一个栏目列表",
		"type": "list"
	},
    "list2": {
		"value": {
		},
		"config": {
			"limit": 4,
			"star_only": 0
		},
		"description": "第二个栏目列表",
		"type": "list"
	},
        "list3": {
		"value": {},
		"config": {
			"limit": 4,
			"star_only": 0
		},
		"description": "第三个栏目列表",
		"type": "list"
	}
}